{
  "name": "Kimpurusha",
  "type": "foe",
  "img": "icons/creatures/abilities/lion-roar-yellow.webp",
  "items": [
    {
      "_id": "TcvH9NHitjyhEqws",
      "name": "Kimpurusha",
      "type": "progress",
      "img": "icons/creatures/abilities/lion-roar-yellow.webp",
      "effects": [],
      "folder": null,
      "sort": 0,
      "flags": {},
      "system": {
        "description": "<div class=\"boxgroup flexrow boxrow\">\n<div class=\"flexcol box\" style=\"justify-content: flex-start;\">\n<h4 class=\"nogrow\" style=\"margin: 0.5em;\">Features</h4>\n<div class=\"page\" title=\"Page 219\">\n<div class=\"layoutArea\">\n<div class=\"column\">\n<p>Lion-headed humanoid</p>\n<p>Flowing beards/manes</p>\n<p>Elegant sherwani jackets and pagri turbans</p>\n</div>\n</div>\n</div>\n</div>\n<div class=\"flexcol box\" style=\"justify-content: flex-start;\">\n<h4 class=\"nogrow\" style=\"margin: 0.5em;\">Drives</h4>\n<div class=\"page\" title=\"Page 219\">\n<div class=\"layoutArea\">\n<div class=\"column\">\n<p>Loyalty to the pride</p>\n<p>Defend their territory</p>\n<p>Following the social hierarchy</p>\n</div>\n</div>\n</div>\n</div>\n<div class=\"flexcol box\" style=\"justify-content: flex-start;\">\n<h4 class=\"nogrow\" style=\"margin: 0.5em;\">Tactics</h4>\n<div class=\"page\" title=\"Page 219\">\n<div class=\"layoutArea\">\n<div class=\"column\">\n<p>Urumi strikes</p>\n<p>Roaring frontal charge</p>\n<p>Draw the circle</p>\n</div>\n</div>\n</div>\n</div>\n</div>\n<div class=\"page\" title=\"Page 220\">\n<div class=\"layoutArea\">\n<div class=\"column\">\n<div class=\"page\" title=\"Page 43\">\n<div class=\"layoutArea\">\n<div class=\"column\">\n<p>Our name for kimpurusha comes from the phrase, &ldquo;Is it human?&rdquo; When we first saw them from afar, we thought their manes were bushy beards, but we could also see the coloration of their fur and feline heads. We continue to refer to them as kimpurusha because they are unwilling to share their own language or culture with us.</p>\n<p>We do know that they are fiercely loyal to each other. The surest way to die in battle against these lion folk is to injure one of them which then enrages the others making them fight doubly hard. It is easier to set your weapons down and admit defeat before the battle even begins. At least that way you have a chance of being allowed to live and let go.</p>\n<p>The other thing we know is that there appears to be a strict pecking order, at least among their warrior groups. The apparent leader of a squad is obeyed without question, but a series of commands are then made by other kimpurusha in an orderly fashion that descend through the ranks.</p>\n<blockquote>\n<p>Quest Starter:</p>\n<p>A kimpurusha settlement was discovered relatively near to a lake that the Tigerlanders are eager to fish. With other food supplies running low due to the inability to grow crops, the overseer wants to make contact with the lion folk and negotiate for use of the lake. What happened the last time you crossed paths with the kimpurusha?</p>\n</blockquote>\n</div>\n</div>\n<div class=\"section\">\n<div class=\"layoutArea\">\n<div class=\"column\">\n<p>&nbsp;</p>\n<blockquote>\n<p><em>Your Truth:</em></p>\n<p><em>The kimpurusha culture is highly honor driven. Does this manifest as a noble, respectful society or as a defensive, easily offended society?</em></p>\n</blockquote>\n</div>\n</div>\n</div>\n</div>\n</div>\n</div>\n</div>",
        "rank": 3,
        "current": 0,
        "completed": false,
        "subtype": "progress",
        "starred": false,
        "hasTrack": true,
        "hasClock": false,
        "clockTicks": 0,
        "clockMax": 6
      },
      "ownership": {
        "default": 0,
        "UxRPXT7DZJSEuDW6": 3
      },
      "_stats": {
        "compendiumSource": null,
        "duplicateSource": null,
        "coreVersion": "12.331",
        "systemId": "foundry-ironsworn",
        "systemVersion": "1.25.0",
        "createdTime": null,
        "modifiedTime": null,
        "lastModifiedBy": null
      },
      "_key": "!actors.items!5KVlzSRy73m8bzap.TcvH9NHitjyhEqws"
    }
  ],
  "effects": [],
  "folder": "1h2u3eK9jX6x0dlp",
  "flags": {
    "core": {
      "sourceId": "Compendium.foundry-ironsworn.foeactorsis.Actor.ETZwkGvsBZoQ7QWl"
    },
    "exportSource": {
      "world": "starforged-development",
      "system": "foundry-ironsworn",
      "coreVersion": "12.331",
      "systemVersion": "1.25.0"
    }
  },
  "system": {
    "dfid": ""
  },
  "ownership": {
    "default": 0,
    "MmM06BuCrG9h1GLg": 3
  },
  "prototypeToken": {
    "name": "Kimpurusha",
    "displayName": 50,
    "actorLink": false,
    "width": 1,
    "height": 1,
    "lockRotation": false,
    "rotation": 0,
    "alpha": 1,
    "light": {
      "alpha": 0.5,
      "angle": 360,
      "bright": 0,
      "coloration": 1,
      "dim": 0,
      "luminosity": 0.5,
      "saturation": 0,
      "contrast": 0,
      "shadows": 0,
      "animation": {
        "speed": 5,
        "intensity": 5,
        "reverse": false,
        "type": null
      },
      "darkness": {
        "min": 0,
        "max": 1
      },
      "attenuation": 0.5,
      "color": null,
      "negative": false,
      "priority": 0
    },
    "disposition": 0,
    "displayBars": 0,
    "bar1": {
      "attribute": null
    },
    "bar2": {
      "attribute": null
    },
    "flags": {},
    "randomImg": false,
    "texture": {
      "src": "icons/creatures/abilities/lion-roar-yellow.webp",
      "scaleX": 1,
      "scaleY": 1,
      "offsetX": 0,
      "offsetY": 0,
      "rotation": 0,
      "tint": "#ffffff",
      "anchorX": 0.5,
      "anchorY": 0.5,
      "fit": "contain",
      "alphaThreshold": 0.75
    },
    "sight": {
      "angle": 360,
      "enabled": false,
      "range": 0,
      "brightness": 1,
      "visionMode": "basic",
      "attenuation": 0.1,
      "saturation": 0,
      "contrast": 0,
      "color": null
    },
    "appendNumber": false,
    "prependAdjective": false,
    "detectionModes": [],
    "hexagonalShape": 0,
    "occludable": {
      "radius": 0
    },
    "ring": {
      "enabled": false,
      "colors": {
        "ring": null,
        "background": null
      },
      "effects": 1,
      "subject": {
        "scale": 1,
        "texture": null
      }
    }
  },
  "_stats": {
    "compendiumSource": "Compendium.foundry-ironsworn.foeactorsis.Actor.ETZwkGvsBZoQ7QWl",
    "duplicateSource": null,
    "coreVersion": "12.331",
    "systemId": "foundry-ironsworn",
    "systemVersion": "1.25.0",
    "createdTime": 1741382275964,
    "modifiedTime": 1741382890181,
    "lastModifiedBy": "MmM06BuCrG9h1GLg"
  },
  "_id": "5KVlzSRy73m8bzap",
  "sort": 100000,
  "_key": "!actors!5KVlzSRy73m8bzap"
}
